putconf/.gitignore
putconf/__about__.py
putconf/__init__.py
putconf/__main__.py
putconf-0.1.0.dist-info/METADATA
putconf-0.1.0.dist-info/WHEEL
putconf-0.1.0.dist-info/entry_points.txt
putconf-0.1.0.dist-info/licenses/LICENSE.txt
putconf-0.1.0.dist-info/RECORD
