Metadata-Version: 2.1
Name: putconf
Version: 0.1.0
Project-URL: Documentation, https://github.com/jepugs/putconf#readme
Project-URL: Issues, https://github.com/jepugs/putconf/issues
Project-URL: Source, https://github.com/jepugs/putconf
Author-email: Jack Pugmire <pugnet.root@gmail.com>
License-Expression: GPL-3.0-or-later
License-File: LICENSE.txt
Classifier: Development Status :: 4 - Beta
Classifier: Programming Language :: Python
Classifier: Programming Language :: Python :: 3.8
Classifier: Programming Language :: Python :: 3.9
Classifier: Programming Language :: Python :: 3.10
Classifier: Programming Language :: Python :: 3.11
Classifier: Programming Language :: Python :: 3.12
Classifier: Programming Language :: Python :: Implementation :: CPython
Classifier: Programming Language :: Python :: Implementation :: PyPy
Requires-Python: >=3.8
